simpleAudioSetup/__init__.py
simpleAudioSetup/audioConfig.py
simpleAudioSetup-0.1.0.dist-info/METADATA
simpleAudioSetup-0.1.0.dist-info/WHEEL
simpleAudioSetup-0.1.0.dist-info/top_level.txt
simpleAudioSetup-0.1.0.dist-info/RECORD
